wexample_helpers_app/__init__.py
wexample_helpers_app/utils/__init__.py
wexample_helpers_app/utils/abstract_kernel.py
wexample_helpers_app/utils/file/__init__.py
wexample_helpers_app-0.0.3.dist-info/METADATA
wexample_helpers_app-0.0.3.dist-info/WHEEL
wexample_helpers_app-0.0.3.dist-info/__init__.py
wexample_helpers_app-0.0.3.dist-info/top_level.txt
wexample_helpers_app-0.0.3.dist-info/RECORD
