Metadata-Version: 2.1
Name: wexample-helpers-app
Version: 0.0.3
Summary: Helpers for building Python app or cli.
Home-page: https://github.com/wexample/python-helpers-app
Author: weeger
Author-email: contact@wexample.com
Classifier: Programming Language :: Python :: 3
Classifier: License :: OSI Approved :: MIT License
Classifier: Operating System :: OS Independent
Requires-Python: >=3.6
Requires-Dist: pydantic
Requires-Dist: python-dotenv
Requires-Dist: wexample-filestate
Requires-Dist: wexample-helpers
Requires-Dist: wexample-prompt
